MANIFEST.in
README.rst
pavement.py
requirements-dev.txt
requirements.txt
setup.py
tox.ini
docs/Makefile
docs/make.bat
docs/source/README
docs/source/conf.py
docs/source/index.rst
docs/source/_static/.gitkeep
pyk8sver/__init__.py
pyk8sver/app.py
pyk8sver/main.py
pyk8sver/metadata.py
pyk8sver.egg-info/PKG-INFO
pyk8sver.egg-info/SOURCES.txt
pyk8sver.egg-info/dependency_links.txt
pyk8sver.egg-info/not-zip-safe
pyk8sver.egg-info/top_level.txt
tests/test_app.py
tests/test_main.py