Metadata-Version: 1.2
Name: pyk8sver
Version: 1.0
Summary: Get k8s version from github
Home-page: https://github.com/sierrezinal/pyk8sver
Author: Gavin Bong
Author-email: rubycoder@gmail.com
Maintainer: Gavin Bong
Maintainer-email: rubycoder@gmail.com
License: UNKNOWN
Platform: UNKNOWN
Classifier: Development Status :: 5 - Production/Stable
Classifier: Environment :: Console
Classifier: Intended Audience :: Developers
Classifier: License :: Other/Proprietary License
Classifier: Natural Language :: English
Classifier: Operating System :: OS Independent
Classifier: Programming Language :: Python :: 3.5
Classifier: Topic :: Documentation
Classifier: Topic :: Software Development :: Libraries :: Python Modules
Classifier: Topic :: System :: Installation/Setup
Classifier: Topic :: System :: Software Distribution
